{
    "config": {
        "iso": "2020-09-07T19:02:33.480110",
        "timestamp": 1599505353.48011
    },
    "db_type_mariadb": {
        "iso": "2020-06-29T02:33:19.608292",
        "timestamp": 1593397999.608292
    },
    "directory_structure": {
        "iso": "2020-09-07T19:02:33.706212",
        "timestamp": 1599505353.706212
    },
    "iana": {
        "iso": "2020-09-07T08:38:15.569507",
        "timestamp": 1599467895.569507
    },
    "psl": {
        "iso": "2020-09-07T08:38:15.651886",
        "timestamp": 1599467895.651886
    },
    "user_agents": {
        "iso": "2020-09-07T08:38:15.706936",
        "timestamp": 1599467895.706936
    }
}